django_db_logger/__init__.py
django_db_logger/admin.py
django_db_logger/apps.py
django_db_logger/config.py
django_db_logger/db_log_handler.py
django_db_logger/models.py
django_db_logger/tests.py
django_db_logger/views.py
django_db_logger/migrations/0001_initial.py
django_db_logger/migrations/0002_auto_20190109_0052.py
django_db_logger/migrations/__init__.py
django_db_logger-0.1.13.dist-info/LICENSE
django_db_logger-0.1.13.dist-info/METADATA
django_db_logger-0.1.13.dist-info/WHEEL
django_db_logger-0.1.13.dist-info/top_level.txt
django_db_logger-0.1.13.dist-info/RECORD
