Metadata-Version: 2.1
Name: django-db-logger
Version: 0.1.13
Summary: Django logging in database
Home-page: https://github.com/CiCiUi/django-db-logger
Author: zhangshine
Author-email: zhangshine0125@gmail.com
License: MIT License
Classifier: Environment :: Web Environment
Classifier: Framework :: Django
Classifier: Intended Audience :: Developers
Classifier: License :: OSI Approved :: MIT License
Classifier: Operating System :: OS Independent
Classifier: Programming Language :: Python
Classifier: Programming Language :: Python :: 3.7
Classifier: Programming Language :: Python :: 3.8
Classifier: Programming Language :: Python :: 3.9
Classifier: Topic :: Internet :: WWW/HTTP
Classifier: Topic :: Internet :: WWW/HTTP :: Dynamic Content
License-File: LICENSE
Requires-Dist: django>=1.9
Requires-Dist: six
